aitsisui/__init__.py
aitsisui/__version.py
aitsisui/app.py
aitsisui/version.txt
aitsisui/core/__init__.py
aitsisui/core/component.py
aitsisui/core/element.py
aitsisui/core/index_gen.py
aitsisui/core/session.py
aitsisui/elements/__init__.py
aitsisui/elements/accordion.py
aitsisui/elements/button.py
aitsisui/elements/canvas.py
aitsisui/elements/check.py
aitsisui/elements/col.py
aitsisui/elements/dropzone.py
aitsisui/elements/file.py
aitsisui/elements/form.py
aitsisui/elements/header.py
aitsisui/elements/htext.py
aitsisui/elements/image.py
aitsisui/elements/imageCropper.py
aitsisui/elements/imageviewer.py
aitsisui/elements/input.py
aitsisui/elements/label.py
aitsisui/elements/link.py
aitsisui/elements/listitem.py
aitsisui/elements/modal.py
aitsisui/elements/option.py
aitsisui/elements/orderedlist.py
aitsisui/elements/page.py
aitsisui/elements/picture.py
aitsisui/elements/radio.py
aitsisui/elements/row.py
aitsisui/elements/select.py
aitsisui/elements/slider.py
aitsisui/elements/source.py
aitsisui/elements/table.py
aitsisui/elements/tbody.py
aitsisui/elements/td.py
aitsisui/elements/text.py
aitsisui/elements/textarea.py
aitsisui/elements/tfoot.py
aitsisui/elements/th.py
aitsisui/elements/thead.py
aitsisui/elements/tr.py
aitsisui/elements/unorderedlist.py
aitsisui/elements/video.py
aitsisui/js/canvas.js
aitsisui/js/dropzone.js
aitsisui/js/font-awesome_6.4.2.all.min.js
aitsisui/js/image_cropper.js
aitsisui/js/jspdf.js
aitsisui/js/main.js
aitsisui/js/main_old.js
aitsisui/js/seadragon.js
aitsisui/js/socket.io.min.js
aitsisui/static/7cH1v4okm5zmbvwkAx_sfcEuiD8jvvKsN9C_nps.woff2
aitsisui/static/7cH1v4okm5zmbvwkAx_sfcEuiD8jvvKsNNC_nps.woff2
aitsisui/static/7cH1v4okm5zmbvwkAx_sfcEuiD8jvvKsNtC_nps.woff2
aitsisui/static/7cH1v4okm5zmbvwkAx_sfcEuiD8jvvKsOdC_.woff2
aitsisui/static/7cH1v4okm5zmbvwkAx_sfcEuiD8jvvKsPdC_nps.woff2
aitsisui/static/AIT_AI_LOGO.png
aitsisui/static/AIT_White.png
aitsisui/static/Exo2.ttf
aitsisui/static/certificate_background.png
aitsisui-0.1.5.dist-info/METADATA
aitsisui-0.1.5.dist-info/WHEEL
aitsisui-0.1.5.dist-info/top_level.txt
aitsisui-0.1.5.dist-info/RECORD
