Metadata-Version: 2.1
Name: aitsisui
Version: 0.1.5
Summary: AIT UI
Author: AIT
Requires-Python: >=3.6
Requires-Dist: Flask
Requires-Dist: Flask-Cors
Requires-Dist: Flask-SocketIO
Requires-Dist: numpy
Requires-Dist: Pillow
Requires-Dist: python-dotenv
